django_json_choices_form_field/__init__.py
django_json_choices_form_field/asgi.py
django_json_choices_form_field/settings.py
django_json_choices_form_field/urls.py
django_json_choices_form_field/wsgi.py
forms/__init__.py
forms/admin.py
forms/forms.py
django_jsonfield_choicefield_form-0.0.1.dist-info/LICENSE
django_jsonfield_choicefield_form-0.0.1.dist-info/METADATA
django_jsonfield_choicefield_form-0.0.1.dist-info/WHEEL
django_jsonfield_choicefield_form-0.0.1.dist-info/top_level.txt
django_jsonfield_choicefield_form-0.0.1.dist-info/RECORD
