Metadata-Version: 2.1
Name: django-jsonfield-choicefield-form
Version: 0.0.1
Summary: django jsonfield with choice field
Home-page: https://github.com/huseyinbilgili/django_jsonfield_choicefield_form
Author: Hüseyin Bilgili
Author-email: hbilgili58@gmail.com
License: UNKNOWN
Platform: UNKNOWN
Classifier: Programming Language :: Python :: 3
Classifier: License :: OSI Approved :: MIT License
Classifier: Operating System :: OS Independent
Requires-Python: >=3.7
